networkmanager/__init__.py
networkmanager/_version.py
networkmanager/exceptions.py
networkmanager/messages.py
networkmanager/networkmanager.py
networkmanager/settings_models.py
networkmanager_python-0.2.1.dist-info/LICENSE
networkmanager_python-0.2.1.dist-info/METADATA
networkmanager_python-0.2.1.dist-info/WHEEL
networkmanager_python-0.2.1.dist-info/top_level.txt
networkmanager_python-0.2.1.dist-info/RECORD
