Metadata-Version: 2.1
Name: networkmanager-python
Version: 0.2.1
Summary: NetworkManager python API using dbus
Author-email: Jakub Kozłowicz <ja.kozlowicz@gmail.com>
License: Copyright 2023 Jakub Kozłowicz
Project-URL: repository, https://gitlab.com/jakub.kozlowicz/python-networkmanager
Project-URL: documentation, https://gitlab.com/jakub.kozlowicz/python-networkmanager
Classifier: Programming Language :: Python :: 3 :: Only
Classifier: Programming Language :: Python :: 3.9
Classifier: Programming Language :: Python :: 3.10
Classifier: Programming Language :: Python :: 3.11
Requires-Python: >=3.9
License-File: LICENSE
Requires-Dist: pydantic (~=1.10.0)
Requires-Dist: dbus-python (~=1.3.0)
Provides-Extra: dev
Requires-Dist: pylint (~=2.16.0) ; extra == 'dev'
Requires-Dist: pylint-pydantic (~=0.1.0) ; extra == 'dev'
Requires-Dist: flake8 (~=6.0.0) ; extra == 'dev'
Requires-Dist: Flake8-pyproject (~=1.2.0) ; extra == 'dev'
Requires-Dist: flake8-comprehensions (~=3.10.0) ; extra == 'dev'
Requires-Dist: flake8-isort (~=6.0.0) ; extra == 'dev'
Requires-Dist: mypy (~=1.0.0) ; extra == 'dev'
Requires-Dist: black (~=23.1.0) ; extra == 'dev'
Requires-Dist: isort (~=5.12.0) ; extra == 'dev'
Requires-Dist: taskipy (~=1.10.0) ; extra == 'dev'
Requires-Dist: pytest (~=7.2.0) ; extra == 'dev'
Requires-Dist: pytest-asyncio (~=0.20.0) ; extra == 'dev'
Requires-Dist: pytest-cov (~=4.0.0) ; extra == 'dev'
Requires-Dist: pytest-stub (~=1.1.0) ; extra == 'dev'
